miscoto/__init__.py
miscoto/__main__.py
miscoto/commons.py
miscoto/miscoto_focus.py
miscoto/miscoto_instance.py
miscoto/miscoto_mincom.py
miscoto/miscoto_scopes.py
miscoto/query.py
miscoto/sbml.py
miscoto/utils.py
miscoto/encodings/community_minexch.lp
miscoto/encodings/community_minexch_nohost.lp
miscoto/encodings/community_soup.lp
miscoto/encodings/iscope_in_community.lp
miscoto/encodings/scopes.lp
Miscoto-3.2.0.dist-info/LICENSE
Miscoto-3.2.0.dist-info/METADATA
Miscoto-3.2.0.dist-info/WHEEL
Miscoto-3.2.0.dist-info/entry_points.txt
Miscoto-3.2.0.dist-info/top_level.txt
Miscoto-3.2.0.dist-info/RECORD
