Metadata-Version: 2.1
Name: Miscoto
Version: 3.2.0
Summary: Microbiome Screening and COmmunity selection using TOpology
Author-email: Clemence Frioux <clemence.frioux@inria.fr>
License: LGPL-3.0-or-later
Project-URL: Homepage, https://github.com/cfrioux/miscoto
Project-URL: Changelog, https://github.com/cfrioux/miscoto/blob/main/CHANGELOG.md
Classifier: Programming Language :: Python :: 3.6
Classifier: Programming Language :: Python :: 3.7
Classifier: Programming Language :: Python :: 3.8
Classifier: Operating System :: MacOS :: MacOS X
Classifier: Operating System :: Unix
License-File: LICENSE
Requires-Dist: clyngor-with-clingo
Requires-Dist: clyngor
